foreninglet_data/__init__.py
foreninglet_data/activities.py
foreninglet_data/api.py
foreninglet_data/data.py
foreninglet_data/memberlist.py
foreninglet_data/models/activities_model.py
foreninglet_data/models/member_model.py
foreninglet_data-0.5.0.dist-info/licenses/LICENSE
foreninglet_data-0.5.0.dist-info/METADATA
foreninglet_data-0.5.0.dist-info/WHEEL
foreninglet_data-0.5.0.dist-info/top_level.txt
foreninglet_data-0.5.0.dist-info/RECORD
