Metadata-Version: 2.4
Name: foreninglet-data
Version: 0.5.0
Summary: A way to retrieve information about members from the ForeningLet API (www.foreninglet.dk) - ForeningLet is a member system for small (typically) voluntary organizations in Denmark
Author-email: Carsten Skov <carsten@simcax.dk>
License: MIT
Requires-Python: >=3.11
License-File: LICENSE
Requires-Dist: dataclasses-json<0.7.0,>=0.5.7
Requires-Dist: requests>=2.31.0
Requires-Dist: pandas>=2.1.4
Requires-Dist: loguru>=0.7.2
Requires-Dist: pydantic>=2.6.4
Requires-Dist: retry>=0.9.2
Requires-Dist: dagger-io>=0.19.8
Provides-Extra: dev
Requires-Dist: black>=23.7.0; extra == "dev"
Requires-Dist: python-dotenv==1.2.1; extra == "dev"
Requires-Dist: dagger-io>=0.19.8; extra == "dev"
Requires-Dist: faker<39.0,>=19.2; extra == "dev"
Requires-Dist: typer<0.21,>=0.9; extra == "dev"
Requires-Dist: sphinx>=7.2.6; extra == "dev"
Requires-Dist: pytest-cov<8.0,>=4.1; extra == "dev"
Requires-Dist: pytest>=8.0.0; extra == "dev"
Requires-Dist: pytest-vcr>=1.0.2; extra == "dev"
Requires-Dist: matplotlib>=3.10.8; extra == "dev"
Dynamic: license-file
